agent_dna-0.3.1.dist-info/licenses/LICENSE
agentdna/__init__.py
agentdna/config.json
agentdna/core.py
agentdna/handler.py
agentdna/node_client.py
agentdna/token.txt
agentdna/trust.py
agent_dna-0.3.1.dist-info/METADATA
agent_dna-0.3.1.dist-info/WHEEL
agent_dna-0.3.1.dist-info/top_level.txt
agent_dna-0.3.1.dist-info/RECORD
