Metadata-Version: 2.4
Name: agent-dna
Version: 0.3.1
Summary: AgentDNA: Verifiable and Auditable AI Agents
Author: Aparna Ullas
License: MIT
Project-URL: Homepage, https://github.com/rubixchain/agentdna
Project-URL: Repository, https://github.com/rubixchain/agentdna
Requires-Python: <3.13,>=3.10
License-File: LICENSE
Requires-Dist: requests>=2.0.0
Requires-Dist: python-dotenv>=1.0.0
Requires-Dist: rubix-py>=0.7.0
Requires-Dist: py-multiformats-cid>=0.4.4
Dynamic: license-file
